salt_viewer/archive.py
salt_viewer/salt_viewer.py
salt_viewer-0.1.14.dist-info/METADATA
salt_viewer-0.1.14.dist-info/WHEEL
salt_viewer-0.1.14.dist-info/entry_points.txt
salt_viewer-0.1.14.dist-info/licenses/LICENSE
salt_viewer-0.1.14.dist-info/RECORD
