Metadata-Version: 2.4
Name: salt-viewer
Version: 0.1.14
Summary: Salt Viewer is a tool for viewing images in an archive or a directory.
Project-URL: Homepage, https://github.com/GuiltyCat/SaltViewer
Author-email: GuiltyCat <37097820+GuiltyCat@users.noreply.github.com>
License-File: LICENSE
Requires-Dist: cairosvg
Requires-Dist: natsort
Requires-Dist: pdf2image
Requires-Dist: pillow
Requires-Dist: pillow-avif-plugin
Requires-Dist: py7zr
Requires-Dist: pypdf3
Requires-Dist: rarfile
Requires-Dist: send2trash
